{
  "id": "122",
  "sourceSlug": "range-rover-vogue-2025-white",
  "name": "Range Rover Vogue 2025 ( White )",
  "brand": "Range Rover",
  "category": "luxury",
  "categories": [
    "luxury",
    "suv",
    "family"
  ],
  "priceDaily": 1350,
  "currency": "AED",
  "specs": {
    "engine": "V8 / 4.4L Turbo Diesel",
    "seats": 5,
    "doors": 5,
    "mileagePerDayKm": 300,
    "transmission": "Automatic",
    "freePickup": true
  },
  "description": "The Range Rover Vogue 2025 blends luxury, performance, and style in a perfect SUV package. With its elegant white exterior, spacious interiors, and advanced features, this vehicle offers a smooth and powerful ride. Renting the Range Rover Vogue 2025 White in Dubai ensures a premium driving experience, ideal for city tours, desert trips, or special occasions.",
  "images": [
    "/images/fleet/122/01.webp",
    "/images/fleet/122/02.webp",
    "/images/fleet/122/03.webp",
    "/images/fleet/122/04.webp",
    "/images/fleet/122/05.webp",
    "/images/fleet/122/06.webp",
    "/images/fleet/122/07.webp",
    "/images/fleet/122/08.webp"
  ],
  "sourceUrl": "/shop/range-rover-vogue-2025-white-122"
}